gradio_imageslider/__init__.py
gradio_imageslider/imageslider.py
gradio_imageslider_momen-0.0.34.dist-info/METADATA
gradio_imageslider_momen-0.0.34.dist-info/WHEEL
gradio_imageslider_momen-0.0.34.dist-info/RECORD
