Metadata-Version: 2.3
Name: gradio_imageslider_momen
Version: 0.0.34
Summary: A Gradio component for comparing two images.  This component can be used in several ways:  - as a **unified input / output** where users will upload a single image and an inference function will generate an image it can be compared to (see demo), - as a **manual upload input** allowing users to compare two of their own images (which can then be passed along elsewhere, e.g. to a model),  - as **static output component** allowing users to compare two images generated by an inference funct
Project-URL: repository, https://github.com/pngwn/gradio-imageslider
Author-email: pngwn <hello@pngwn.io>
License-Expression: Apache-2.0
Keywords: gradio,gradio custom component,machine learning,reproducibility,visualization
Classifier: Development Status :: 3 - Alpha
Classifier: License :: OSI Approved :: Apache Software License
Classifier: Operating System :: OS Independent
Classifier: Programming Language :: Python :: 3
Classifier: Programming Language :: Python :: 3 :: Only
Classifier: Programming Language :: Python :: 3.8
Classifier: Programming Language :: Python :: 3.9
Classifier: Programming Language :: Python :: 3.10
Classifier: Programming Language :: Python :: 3.11
Classifier: Topic :: Scientific/Engineering
Classifier: Topic :: Scientific/Engineering :: Artificial Intelligence
Classifier: Topic :: Scientific/Engineering :: Visualization
Requires-Python: >=3.9
Requires-Dist: gradio
Requires-Dist: pillow
